zoomer/__init__.py
zoomer/__version__.py
zoomer/base.py
zoomer/face.py
zoomer/facedetect.py
zoomer/run.py
zoomer/test.py
Zoomer-0.1.3.dist-info/LICENSE
Zoomer-0.1.3.dist-info/METADATA
Zoomer-0.1.3.dist-info/WHEEL
Zoomer-0.1.3.dist-info/top_level.txt
Zoomer-0.1.3.dist-info/RECORD
