Metadata-Version: 2.1
Name: Zoomer
Version: 0.1.3
Summary: Zoomer is an open source face recognition lib
Home-page: https://github.com/RoWe98/Zoomer
Author: RoWe98
Author-email: wzx8551517@163.com
License: MIT
Platform: UNKNOWN
